[
  {
    "name": "elle s au cinema sarah bernhardt la divine",
    "title": "Elle(s) au cinéma : Sarah Bernhardt, La Divine",
    "source": "pathe",
    "showId": "V3132S76228",
    "linkShow": "https://s.pathe.fr/fr/V3132S76228/booking",
    "earlyType": "AVP",
    "movieId": "elle-s-au-cinema-sarah-bernhardt-la-divine-42809",
    "linkMovie": "https://www.pathe.fr/films/elle-s-au-cinema-sarah-bernhardt-la-divine-42809",
    "cinemaName": "pathe-cinema-pathe-alesia",
    "version": "vf",
    "dateShow": "2024-12-15T16:45:00.000Z",
    "cover": "https://media.pathe.fr/movie/alex/HO00008479/poster/lg/14/movie&uuid=1195E517-36E2-467E-8CC9-50F43E09B7E1",
    "officialRelease": "2024-12-15T00:00:00.000Z",
    "db": {
      "id": "",
      "title": "",
      "poster": ""
    },
    "imdb": {
      "id": "",
      "title": "",
      "poster": ""
    },
    "allocine": {
      "id": "",
      "title": "",
      "poster": ""
    },
    "tmdb": null
  },
  {
    "name": "elle s au cinema sarah bernhardt la divine",
    "title": "Elle(s) au cinéma : Sarah Bernhardt, La Divine",
    "source": "pathe",
    "showId": "V3128S144493",
    "linkShow": "https://s.pathe.fr/fr/V3128S144493/booking",
    "earlyType": "AVP",
    "movieId": "elle-s-au-cinema-sarah-bernhardt-la-divine-42809",
    "linkMovie": "https://www.pathe.fr/films/elle-s-au-cinema-sarah-bernhardt-la-divine-42809",
    "cinemaName": "pathe-cinema-pathe-parnasse",
    "version": "vf",
    "dateShow": "2024-12-15T17:00:00.000Z",
    "cover": "https://media.pathe.fr/movie/alex/HO00008479/poster/lg/14/movie&uuid=1195E517-36E2-467E-8CC9-50F43E09B7E1",
    "officialRelease": "2024-12-15T00:00:00.000Z",
    "db": {
      "id": "",
      "title": "",
      "poster": ""
    },
    "imdb": {
      "id": "",
      "title": "",
      "poster": ""
    },
    "allocine": {
      "id": "",
      "title": "",
      "poster": ""
    },
    "tmdb": null
  },
  {
    "name": "my sunshine",
    "title": "My Sunshine",
    "source": "pathe",
    "showId": "V3136S94838",
    "linkShow": "https://s.pathe.fr/fr/V3136S94838/booking",
    "earlyType": "AVPE",
    "movieId": "my-sunshine-38861",
    "linkMovie": "https://www.pathe.fr/films/my-sunshine-38861",
    "cinemaName": "pathe-cinema-pathe-convention",
    "version": "vost",
    "dateShow": "2024-12-11T12:30:00.000Z",
    "cover": "https://media.pathe.fr/movie/alex/HO00007635/poster/lg/169/movie&uuid=F2198DA8-8F32-470C-9B03-9BF53D3F97A6",
    "officialRelease": "2024-12-25T00:00:00.000Z",
    "db": {
      "id": "tt22694908",
      "title": "Boku no ohisama",
      "poster": "https://m.media-amazon.com/images/M/MV5BMjQwM2Q5Y2ItNjJjNy00OGI2LWIxMmItY2ZkZmE4NjZiZGMyXkEyXkFqcGc@._V1_.jpg"
    },
    "imdb": {
      "id": "tt22694908",
      "title": "Boku no ohisama",
      "poster": "https://m.media-amazon.com/images/M/MV5BMjQwM2Q5Y2ItNjJjNy00OGI2LWIxMmItY2ZkZmE4NjZiZGMyXkEyXkFqcGc@._V1_.jpg"
    },
    "allocine": {
      "id": "",
      "title": "",
      "poster": ""
    },
    "tmdb": {
      "id": 1267822,
      "title": "My Sunshine",
      "poster": "https://image.tmdb.org/t/p/w600_and_h900_bestv2/yo9t3HZkvczLBnu2eGgYT1IMVf0.jpg"
    }
  },
  {
    "name": "sarah bernhardt la divine",
    "title": "Sarah Bernhardt, la divine",
    "source": "pathe",
    "showId": "V3136S91659",
    "linkShow": "https://s.pathe.fr/fr/V3136S91659/booking",
    "earlyType": "AVPE",
    "movieId": "sarah-bernhardt-la-divine-39853",
    "linkMovie": "https://www.pathe.fr/films/sarah-bernhardt-la-divine-39853",
    "cinemaName": "pathe-cinema-pathe-convention",
    "version": "vf",
    "dateShow": "2024-12-16T18:30:00.000Z",
    "cover": "https://media.pathe.fr/movie/alex/HO00007784/poster/lg/49/movie&uuid=EECF1B97-835E-460D-9EA1-9DE33AF2447D",
    "officialRelease": "2024-12-18T00:00:00.000Z",
    "db": {
      "id": "tt33298403",
      "title": "Sarah Bernhardt, la divine",
      "poster": "https://m.media-amazon.com/images/M/MV5BZGIyYThlZDItNTdjNC00MGI0LThkYjAtNTgxNWIxMzNiNTc1XkEyXkFqcGc@._V1_.jpg"
    },
    "imdb": {
      "id": "tt33298403",
      "title": "Sarah Bernhardt, la divine",
      "poster": "https://m.media-amazon.com/images/M/MV5BZGIyYThlZDItNTdjNC00MGI0LThkYjAtNTgxNWIxMzNiNTc1XkEyXkFqcGc@._V1_.jpg"
    },
    "allocine": {
      "id": "",
      "title": "",
      "poster": ""
    },
    "tmdb": {
      "id": 1228322,
      "title": "Sarah Bernhardt, la divine",
      "poster": "https://image.tmdb.org/t/p/w600_and_h900_bestv2/7CQ2INq1esJABak8VlkSNPGH9ea.jpg"
    }
  },
  {
    "name": "la seance live le deluge",
    "title": "le déluge",
    "source": "pathe",
    "showId": "V3136S94444",
    "linkShow": "https://s.pathe.fr/fr/V3136S94444/booking",
    "earlyType": "AVPE",
    "movieId": "la-seance-live-le-deluge-42833",
    "linkMovie": "https://www.pathe.fr/films/la-seance-live-le-deluge-42833",
    "cinemaName": "pathe-cinema-pathe-convention",
    "version": "vf",
    "dateShow": "2024-12-10T18:45:00.000Z",
    "cover": "https://media.pathe.fr/movie/alex/HO00008503/poster/lg/3/movie&uuid=9B478DD4-B7AF-427A-A412-5C6D839A0ECB",
    "officialRelease": "2024-12-10T00:00:00.000Z",
    "db": {
      "id": "tt27641422",
      "title": "Le Déluge",
      "poster": "https://m.media-amazon.com/images/M/MV5BYzgyNDJjZjItMTg5NS00OWNjLWFmOTQtZWNmOGM2YzhkYWMwXkEyXkFqcGc@._V1_.jpg"
    },
    "imdb": {
      "id": "tt27641422",
      "title": "Le Déluge",
      "poster": "https://m.media-amazon.com/images/M/MV5BYzgyNDJjZjItMTg5NS00OWNjLWFmOTQtZWNmOGM2YzhkYWMwXkEyXkFqcGc@._V1_.jpg"
    },
    "allocine": {
      "id": "",
      "title": "",
      "poster": ""
    },
    "tmdb": {
      "id": 1091275,
      "title": "Le Déluge",
      "poster": "https://image.tmdb.org/t/p/w600_and_h900_bestv2/13w7MgjQcXVbFB5hUBH9DC9Inbc.jpg"
    }
  },
  {
    "imdb": {
      "id": "tt27503400",
      "title": "Animale",
      "poster": "https://m.media-amazon.com/images/M/MV5BMTVhN2M1MTktNDI4ZS00ZWM5LThhNjgtYWYxOWVmN2RiYTk1XkEyXkFqcGc@._V1_.jpg"
    },
    "allocine": {
      "id": "",
      "title": "",
      "poster": ""
    },
    "tmdb": {
      "id": 1020822,
      "title": "Animale",
      "poster": "https://image.tmdb.org/t/p/w600_and_h900_bestv2/pBa0Rmp4AVjbFXtJOPVsw6gnk4P.jpg"
    },
    "db": {
      "id": "tt27503400",
      "title": "Animale",
      "poster": "https://m.media-amazon.com/images/M/MV5BMTVhN2M1MTktNDI4ZS00ZWM5LThhNjgtYWYxOWVmN2RiYTk1XkEyXkFqcGc@._V1_.jpg"
    },
    "name": "animale",
    "title": "Animale",
    "source": "ugc",
    "officialRelease": "2024-11-26T23:00:00.000Z",
    "showId": "330171726359",
    "linkShow": "https://www.ugc.fr/reservationSeances.html?id=330171726359",
    "earlyType": "AVPE",
    "cover": "https://www.ugc.fr/dynamique/films/25/16325/fr/poster/large/002a3e6ef13c7fab43256a78a358612f_679.jpg",
    "movieId": "16325",
    "linkMovie": "https://www.ugc.fr/film.html?id=16325",
    "cinemaName": "ugc-cine-cite-les-halles",
    "version": "vf",
    "dateShow": "2024-11-25T19:15:00.000Z"
  },
  {
    "imdb": {
      "id": "tt28277817",
      "title": "Bird",
      "poster": "https://m.media-amazon.com/images/M/MV5BMGYzZDI4OTktZWJkZC00NjdiLTlkMjYtMzA1ZTVjMDU2M2FhXkEyXkFqcGc@._V1_.jpg"
    },
    "allocine": {
      "id": "",
      "title": "",
      "poster": ""
    },
    "tmdb": {
      "id": 1128752,
      "title": "Bird",
      "poster": "https://image.tmdb.org/t/p/w600_and_h900_bestv2/96LljvrTGesFPzRiytTrBgPV8W9.jpg"
    },
    "db": {
      "id": "tt28277817",
      "title": "Bird",
      "poster": "https://m.media-amazon.com/images/M/MV5BMGYzZDI4OTktZWJkZC00NjdiLTlkMjYtMzA1ZTVjMDU2M2FhXkEyXkFqcGc@._V1_.jpg"
    },
    "name": "bird",
    "title": "Bird",
    "source": "ugc",
    "officialRelease": "2024-12-31T23:00:00.000Z",
    "showId": "330171726479",
    "linkShow": "https://www.ugc.fr/reservationSeances.html?id=330171726479",
    "earlyType": "AVPE",
    "cover": "https://www.ugc.fr/dynamique/images/affiches/bird_330x440.jpg",
    "movieId": "16347",
    "linkMovie": "https://www.ugc.fr/film.html?id=16347",
    "cinemaName": "ugc-cine-cite-les-halles",
    "version": "vost",
    "dateShow": "2024-11-28T19:15:00.000Z"
  },
  {
    "imdb": {
      "id": "tt20215234",
      "title": "Konkláve",
      "poster": "https://m.media-amazon.com/images/M/MV5BYjgxMDI5NmMtNTU3OS00ZDQxLTgxZmEtNzY1ZTBmMDY4NDRkXkEyXkFqcGc@._V1_.jpg"
    },
    "allocine": {
      "id": "",
      "title": "",
      "poster": ""
    },
    "tmdb": {
      "id": 974576,
      "title": "Conclave",
      "poster": "https://image.tmdb.org/t/p/w600_and_h900_bestv2/fXtwta35Hph8e95HwPQrdavSbqu.jpg"
    },
    "db": {
      "id": "tt20215234",
      "title": "Konkláve",
      "poster": "https://m.media-amazon.com/images/M/MV5BYjgxMDI5NmMtNTU3OS00ZDQxLTgxZmEtNzY1ZTBmMDY4NDRkXkEyXkFqcGc@._V1_.jpg"
    },
    "name": "conclave",
    "title": "Conclave",
    "source": "ugc",
    "officialRelease": null,
    "showId": "330020270485",
    "linkShow": "https://www.ugc.fr/reservationSeances.html?id=330020270485",
    "earlyType": "AVP",
    "cover": "https://www.ugc.fr/dynamique/films/56/16256/fr/poster/large/493b675678d0a26dbcbd3c3982975af4_21.jpg",
    "movieId": "16256",
    "linkMovie": "https://www.ugc.fr/film.html?id=16256",
    "cinemaName": "ugc-cine-cite-maillot",
    "version": "vost",
    "dateShow": "2024-12-01T18:00:00.000Z"
  },
  {
    "imdb": {
      "id": "tt30327451",
      "title": "En fanfare",
      "poster": "https://m.media-amazon.com/images/M/MV5BYTI1N2ZmNWMtOTFkMi00ZDA5LTk3NjktMWE5NGEzOTgzODc1XkEyXkFqcGc@._V1_.jpg"
    },
    "allocine": {
      "id": "",
      "title": "",
      "poster": ""
    },
    "tmdb": {
      "id": 1000866,
      "title": "En fanfare",
      "poster": "https://image.tmdb.org/t/p/w600_and_h900_bestv2/knB9YhFbWjAjHwD3a3W9fhfoOuW.jpg"
    },
    "db": {
      "id": "tt30327451",
      "title": "En fanfare",
      "poster": "https://m.media-amazon.com/images/M/MV5BYTI1N2ZmNWMtOTFkMi00ZDA5LTk3NjktMWE5NGEzOTgzODc1XkEyXkFqcGc@._V1_.jpg"
    },
    "name": "en fanfare",
    "title": "En fanfare",
    "source": "ugc",
    "officialRelease": "2024-11-26T23:00:00.000Z",
    "showId": "330041001319",
    "linkShow": "https://www.ugc.fr/reservationSeances.html?id=330041001319",
    "earlyType": "AVPE",
    "cover": "https://www.ugc.fr/dynamique/films/51/16351/fr/poster/large/647422e028e4ec2074828047f69efa08_31.jpg",
    "movieId": "16351",
    "linkMovie": "https://www.ugc.fr/film.html?id=16351",
    "cinemaName": "ugc-danton",
    "version": "vf",
    "dateShow": "2024-11-25T19:15:00.000Z"
  },
  {
    "imdb": {
      "id": "tt32749982",
      "title": "Il était une fois Michel Legrand",
      "poster": "https://m.media-amazon.com/images/M/MV5BZmQ4OWMwOTUtMzA4OS00YjVlLThmMjUtNTA3ZGM2MTE0OTNlXkEyXkFqcGc@._V1_.jpg"
    },
    "allocine": {
      "id": "",
      "title": "",
      "poster": ""
    },
    "tmdb": {
      "id": 1280476,
      "title": "Il était une fois Michel Legrand",
      "poster": "https://image.tmdb.org/t/p/w600_and_h900_bestv2/tAeHKEDC1jeoJ1WcK8MLkPFXlm2.jpg"
    },
    "db": {
      "id": "tt32749982",
      "title": "Il était une fois Michel Legrand",
      "poster": "https://m.media-amazon.com/images/M/MV5BZmQ4OWMwOTUtMzA4OS00YjVlLThmMjUtNTA3ZGM2MTE0OTNlXkEyXkFqcGc@._V1_.jpg"
    },
    "name": "il etait une fois michel legrand",
    "title": "Il etait une fois michel legrand",
    "source": "ugc",
    "officialRelease": null,
    "showId": "330171726480",
    "linkShow": "https://www.ugc.fr/reservationSeances.html?id=330171726480",
    "earlyType": "AVPE",
    "cover": "https://www.ugc.fr/dynamique/films/22/16422/fr/poster/large/422846c42285a900aa427fc6f86936a8_22.jpg",
    "movieId": "16422",
    "linkMovie": "https://www.ugc.fr/film.html?id=16422",
    "cinemaName": "ugc-cine-cite-les-halles",
    "version": "vf",
    "dateShow": "2024-11-29T19:15:00.000Z"
  },
  {
    "imdb": {},
    "allocine": {
      "id": "",
      "title": "",
      "poster": ""
    },
    "tmdb": {
      "id": 1020969,
      "title": "Le Noël de Teddy l'ourson",
      "poster": "https://image.tmdb.org/t/p/w600_and_h900_bestv2/xegXeb1LbFcU9fR2ZNZw4eColY0.jpg"
    },
    "db": {},
    "name": "le noël de teddy l'ourson",
    "title": "Le noël de teddy l'ourson",
    "source": "ugc",
    "officialRelease": null,
    "showId": "330020269466",
    "linkShow": "https://www.ugc.fr/reservationSeances.html?id=330020269466",
    "earlyType": "AVP",
    "cover": "https://www.ugc.fr/dynamique/films/41/15541/fr/poster/large/5496683_169.jpg",
    "movieId": "15541",
    "linkMovie": "https://www.ugc.fr/film.html?id=15541",
    "cinemaName": "ugc-cine-cite-maillot",
    "version": "vf",
    "dateShow": "2024-12-08T10:00:00.000Z"
  },
  {
    "imdb": {
      "id": "tt28522540",
      "title": "Leurs enfants après eux",
      "poster": "https://m.media-amazon.com/images/M/MV5BNWEwNjhkMjEtNmRhMC00MjNjLWE2YTYtZGU0ZDg4NDRjYzgyXkEyXkFqcGc@._V1_.jpg"
    },
    "allocine": {
      "id": "",
      "title": "",
      "poster": ""
    },
    "tmdb": {
      "id": 1103678,
      "title": "Leurs enfants après eux",
      "poster": "https://image.tmdb.org/t/p/w600_and_h900_bestv2/udvRKoORCX4VqJn5bN8f9w2nTl2.jpg"
    },
    "db": {
      "id": "tt28522540",
      "title": "Leurs enfants après eux",
      "poster": "https://m.media-amazon.com/images/M/MV5BNWEwNjhkMjEtNmRhMC00MjNjLWE2YTYtZGU0ZDg4NDRjYzgyXkEyXkFqcGc@._V1_.jpg"
    },
    "name": "leurs enfants après eux",
    "title": "Leurs enfants après eux",
    "source": "ugc",
    "officialRelease": null,
    "showId": "330091428757",
    "linkShow": "https://www.ugc.fr/reservationSeances.html?id=330091428757",
    "earlyType": "AVP",
    "cover": "https://www.ugc.fr/dynamique/films/14/16114/fr/poster/large/ec9d428026d3f05cddf9a749512008df_21.jpg",
    "movieId": "16114",
    "linkMovie": "https://www.ugc.fr/film.html?id=16114",
    "cinemaName": "ugc-cine-cite-bercy",
    "version": "vf",
    "dateShow": "2024-12-01T17:05:00.000Z"
  },
  {
    "imdb": {
      "id": "tt14813816",
      "title": "Sobík Niko: Cesta za polární záři",
      "poster": "https://m.media-amazon.com/images/M/MV5BZWYyZGNjMjMtYTIxMi00ZmNkLWFhOTYtMjU5OWVhODYxMTQwXkEyXkFqcGc@._V1_.jpg"
    },
    "allocine": {
      "id": "",
      "title": "",
      "poster": ""
    },
    "tmdb": {
      "id": 717196,
      "title": "Niko le petit renne, mission Père Noël",
      "poster": "https://image.tmdb.org/t/p/w600_and_h900_bestv2/55KEwlAraIcmYM4WmaZz0CeweiD.jpg"
    },
    "db": {
      "id": "tt14813816",
      "title": "Sobík Niko: Cesta za polární záři",
      "poster": "https://m.media-amazon.com/images/M/MV5BZWYyZGNjMjMtYTIxMi00ZmNkLWFhOTYtMjU5OWVhODYxMTQwXkEyXkFqcGc@._V1_.jpg"
    },
    "name": "niko le petit renne, mission père nöel",
    "title": "Niko le petit renne, mission père nöel",
    "source": "ugc",
    "officialRelease": null,
    "showId": "330020269467",
    "linkShow": "https://www.ugc.fr/reservationSeances.html?id=330020269467",
    "earlyType": "AVP",
    "cover": "https://www.ugc.fr/dynamique/films/03/16103/fr/poster/large/01ef3db776a88ed6cd1b73ccc32f6e10_18.jpg",
    "movieId": "16103",
    "linkMovie": "https://www.ugc.fr/film.html?id=16103",
    "cinemaName": "ugc-cine-cite-maillot",
    "version": "vf",
    "dateShow": "2024-12-01T10:00:00.000Z"
  },
  {
    "imdb": {
      "id": "tt33298252",
      "title": "Rabia",
      "poster": "https://m.media-amazon.com/images/M/MV5BNmRlY2U3ZTYtOGVkOC00YzFiLTgwMDgtNWYyNWM0NjYzMzgzXkEyXkFqcGc@._V1_.jpg"
    },
    "allocine": {
      "id": "",
      "title": "",
      "poster": ""
    },
    "tmdb": {
      "id": 999142,
      "title": "Rabia",
      "poster": "https://image.tmdb.org/t/p/w600_and_h900_bestv2/3XSp7cBOELTYuoUGAcSe9lSCxHu.jpg"
    },
    "db": {
      "id": "tt33298252",
      "title": "Rabia",
      "poster": "https://m.media-amazon.com/images/M/MV5BNmRlY2U3ZTYtOGVkOC00YzFiLTgwMDgtNWYyNWM0NjYzMzgzXkEyXkFqcGc@._V1_.jpg"
    },
    "name": "rabia",
    "title": "Rabia",
    "source": "ugc",
    "officialRelease": "2024-11-26T23:00:00.000Z",
    "showId": "330171726361",
    "linkShow": "https://www.ugc.fr/reservationSeances.html?id=330171726361",
    "earlyType": "AVPE",
    "cover": "https://www.ugc.fr/dynamique/films/26/16426/fr/poster/large/539e1948c4b76127ff44b39322480503_42.jpg",
    "movieId": "16426",
    "linkMovie": "https://www.ugc.fr/film.html?id=16426",
    "cinemaName": "ugc-cine-cite-les-halles",
    "version": "vf",
    "dateShow": "2024-11-26T19:15:00.000Z"
  },
  {
    "imdb": {
      "id": "tt33298403",
      "title": "Sarah Bernhardt, la divine",
      "poster": "https://m.media-amazon.com/images/M/MV5BZGIyYThlZDItNTdjNC00MGI0LThkYjAtNTgxNWIxMzNiNTc1XkEyXkFqcGc@._V1_.jpg"
    },
    "allocine": {
      "id": "",
      "title": "",
      "poster": ""
    },
    "tmdb": {
      "id": 1228322,
      "title": "Sarah Bernhardt, la divine",
      "poster": "https://image.tmdb.org/t/p/w600_and_h900_bestv2/7CQ2INq1esJABak8VlkSNPGH9ea.jpg"
    },
    "db": {
      "id": "tt33298403",
      "title": "Sarah Bernhardt, la divine",
      "poster": "https://m.media-amazon.com/images/M/MV5BZGIyYThlZDItNTdjNC00MGI0LThkYjAtNTgxNWIxMzNiNTc1XkEyXkFqcGc@._V1_.jpg"
    },
    "name": "sarah bernhardt, la divine",
    "title": "Sarah bernhardt, la divine",
    "source": "ugc",
    "officialRelease": null,
    "showId": "330091428012",
    "linkShow": "https://www.ugc.fr/reservationSeances.html?id=330091428012",
    "earlyType": "AVPE",
    "cover": "https://www.ugc.fr/dynamique/films/68/16368/fr/poster/large/cc0e6e4328ea387fd49c52672328698f_104.jpg",
    "movieId": "16368",
    "linkMovie": "https://www.ugc.fr/film.html?id=16368",
    "cinemaName": "ugc-cine-cite-bercy",
    "version": "vf",
    "dateShow": "2024-12-11T09:00:00.000Z"
  }
]