[
  {
    "name": "super lion",
    "showId": "",
    "movieId": "super-lion-19574",
    "cinemaName": "cinema-pathe-alesia",
    "dateShow": "2024-05-01T10:30:00.000Z",
    "linkMovie": "https://www.pathe.fr/films/super-lion-19574",
    "linkShow": "https://s.pathe.fr/fr/V3132S64527/booking",
    "version": "vf",
    "earlyType": "AVP",
    "source": "pathe"
  },
  {
    "name": "super lion",
    "showId": "",
    "movieId": "super-lion-19574",
    "cinemaName": "cinema-gaumont-aquaboulevard",
    "dateShow": "2024-05-01T11:00:00.000Z",
    "linkMovie": "https://www.pathe.fr/films/super-lion-19574",
    "linkShow": "https://s.pathe.fr/fr/V3140S94486/booking",
    "version": "vf",
    "earlyType": "AVP",
    "source": "pathe"
  },
  {
    "name": "les vendredis de l horreur abigail",
    "showId": "",
    "movieId": "les-vendredis-de-l-horreur-abigail-38783",
    "cinemaName": "cinema-pathe-la-villette",
    "dateShow": "2024-05-24T22:00:00.000Z",
    "linkMovie": "https://www.pathe.fr/films/les-vendredis-de-l-horreur-abigail-38783",
    "linkShow": "https://s.pathe.fr/fr/V3168S109846/booking",
    "version": "vf",
    "earlyType": "AVP",
    "source": "pathe"
  },
  {
    "name": "comme un lundi",
    "showId": "",
    "movieId": "comme-un-lundi-35204",
    "cinemaName": "cinema-pathe-parnasse",
    "dateShow": "2024-05-06T20:00:00.000Z",
    "linkMovie": "https://www.pathe.fr/films/comme-un-lundi-35204",
    "linkShow": "https://s.pathe.fr/fr/V3128S128098/booking",
    "version": "vost",
    "earlyType": "AVP",
    "source": "pathe"
  },
  {
    "name": "comme un lundi",
    "showId": "",
    "movieId": "comme-un-lundi-35204",
    "cinemaName": "cinema-pathe-wepler",
    "dateShow": "2024-05-06T20:00:00.000Z",
    "linkMovie": "https://www.pathe.fr/films/comme-un-lundi-35204",
    "linkShow": "https://s.pathe.fr/fr/V3010S101768/booking",
    "version": "vost",
    "earlyType": "AVP",
    "source": "pathe"
  }
]